MANIFEST.in
README.md
setup.cfg
setup.py
dev0s/.version
dev0s/__init__.py
dev0s/__main__.py
dev0s/shortcuts.py
dev0s.egg-info/PKG-INFO
dev0s.egg-info/SOURCES.txt
dev0s.egg-info/dependency_links.txt
dev0s.egg-info/not-zip-safe
dev0s.egg-info/requires.txt
dev0s.egg-info/top_level.txt
dev0s/classes/__init__.py
dev0s/classes/cli/__init__.py
dev0s/classes/code/__init__.py
dev0s/classes/code/execute.py
dev0s/classes/config/__init__.py
dev0s/classes/console/__init__.py
dev0s/classes/database/__init__.py
dev0s/classes/database/fork.py
dev0s/classes/defaults/__init__.py
dev0s/classes/defaults/color.py
dev0s/classes/defaults/defaults.py
dev0s/classes/defaults/exceptions.py
dev0s/classes/defaults/files.py
dev0s/classes/defaults/objects.py
dev0s/classes/encryption/__init__.py
dev0s/classes/encryption/aes.py
dev0s/classes/encryption/agent.py
dev0s/classes/encryption/rsa.py
dev0s/classes/manager/__init__.py
dev0s/classes/manager/installation.py
dev0s/classes/messaging/__init__.py
dev0s/classes/messaging/telegram.py
dev0s/classes/network/__init__.py
dev0s/classes/network/firewall.py
dev0s/classes/network/wifi.py
dev0s/classes/requests/__init__.py
dev0s/classes/response/__init__.py
dev0s/classes/system/__init__.py
dev0s/classes/system/browser.py
dev0s/classes/system/cleanup.py
dev0s/classes/system/disks.py
dev0s/classes/system/env.py
dev0s/classes/system/metrics.py
dev0s/classes/system/service.py
dev0s/classes/system/system.py
dev0s/classes/utils/__init__.py
dev0s/classes/utils/copycats.py
dev0s/lib/bash/env
dev0s/lib/bash/import
dev0s/lib/bash/packages
dev0s/lib/bash/pull_push
dev0s/lib/bash/utils
dev0s/lib/js/dev0s.html
dev0s/lib/python/comment.py
dev0s/lib/python/example
dev0s/lib/python/find-str-in-dir
dev0s/lib/python/replace-str-in-dir