Metadata-Version: 1.0
Name: dev0s
Version: 3.35.5
Summary: Some description.
Home-page: http://github.com/vandenberghinc/dev0s
Author: Daan van den Bergh
Author-email: vandenberghinc.contact@gmail.com
License: MIT
Platform: UNKNOWN
